[{"jobTitle":"Database Manager","id":0,"firstName":"Yeshua","lastName":"Magana","hairColor":"Black","eyeColor":"Blue","age":44,"weight":61.4,"height":166,"sex":"M"},{"jobTitle":"Captain","id":1,"firstName":"Jayden","lastName":"Harrell","hairColor":"Leverpostej","eyeColor":"Brown","age":43,"weight":76.6,"height":145,"sex":"F"},{"jobTitle":"Veterenarian","id":2,"firstName":"Titus","lastName":"England","hairColor":"Red","eyeColor":"Brown","age":45,"weight":70.8,"height":177,"sex":"M"},{"jobTitle":"Personal Trainer","id":3,"firstName":"Zaid","lastName":"Dalton","hairColor":"Black","eyeColor":"Blue","age":38,"weight":34.8,"height":179,"sex":"M"},{"jobTitle":"Talent Acquisition Coordinator","id":4,"firstName":"Ulises","lastName":"Lewis","hairColor":"Black","eyeColor":"Brown","age":51,"weight":32.4,"height":177,"sex":"M"},{"jobTitle":"Electrical Engineer","id":5,"firstName":"Colt","lastName":"Lewis","hairColor":"Black","eyeColor":"Grey","age":42,"weight":76.6,"height":179,"sex":"M"},{"jobTitle":"Front Desk Coordinator","id":6,"firstName":"Zaynab","lastName":"Schultz","hairColor":"Black","eyeColor":"Grey","age":34,"weight":150,"height":160,"sex":"F"},{"jobTitle":"Aquatic Ecologist","id":7,"firstName":"Kaidence","lastName":"Ferguson","hairColor":"Brown","eyeColor":"Brown","age":37,"weight":65.8,"height":162,"sex":"F"},{"jobTitle":"Casino Host","id":8,"firstName":"Magnus","lastName":"Rivas","hairColor":"Brown","eyeColor":"Brown","age":53,"weight":67.4,"height":171,"sex":"M"},{"jobTitle":"Chemist","id":9,"firstName":"Zayne","lastName":"Douglas","hairColor":"Black","eyeColor":"Grey","age":48,"weight":78.6,"height":169,"sex":"M"},{"jobTitle":"Business Development Manager","id":10,"firstName":"Mustafa","lastName":"Mckay","hairColor":"Black","eyeColor":"Brown","age":51,"weight":76,"height":165,"sex":"M"},{"jobTitle":"Hairdresser","id":11,"firstName":"Landry","lastName":"Armstrong","hairColor":"Brown","eyeColor":"Blue","age":58,"weight":116.6,"height":173,"sex":"M"},{"jobTitle":"Meeting Planner","id":12,"firstName":"Jace","lastName":"Orr","hairColor":"Green","eyeColor":"Grey","age":51,"weight":71.4,"height":171,"sex":"M"},{"jobTitle":"Gardener","id":13,"firstName":"Kehlani","lastName":"Hernandez","hairColor":"Black","eyeColor":"Brown","age":45,"weight":30.2,"height":166,"sex":"F"},{"jobTitle":"ITManager","id":14,"firstName":"Skylah","lastName":"Hernandez","hairColor":"Brown","eyeColor":"Green","age":38,"weight":103,"height":179,"sex":"F"},{"jobTitle":"Business Reporter","id":15,"firstName":"Estefania","lastName":"Harper","hairColor":"Black","eyeColor":"Brown","age":31,"weight":35.8,"height":159,"sex":"F"},{"jobTitle":"Producer","id":16,"firstName":"Evangeline","lastName":"Harvey","hairColor":"Black","eyeColor":"Brown","age":57,"weight":29.2,"height":136,"sex":"F"},{"jobTitle":"Factory Worker","id":17,"firstName":"Kailey","lastName":"Phelps","hairColor":"Black","eyeColor":"Blue","age":38,"weight":69.4,"height":156,"sex":"F"},{"jobTitle":"Dietitian","id":18,"firstName":"Rayne","lastName":"Kirby","hairColor":"Black","eyeColor":"Hazel","age":41,"weight":105.6,"height":180,"sex":"F"},{"jobTitle":"Human Resources Director","id":19,"firstName":"Izayah","lastName":"Fischer","hairColor":"Black","eyeColor":"Brown","age":45,"weight":102.5,"height":178,"sex":"M"},{"jobTitle":"Superintendent","id":20,"firstName":"Siddharth","lastName":"Perkins","hairColor":"Black","eyeColor":"Brown","age":53,"weight":43.8,"height":179,"sex":"M"},{"jobTitle":"Civil Engineer","id":21,"firstName":"Dayra","lastName":"Perkins","hairColor":"Black","eyeColor":"Brown","age":50,"weight":82.5,"height":157,"sex":"F"},{"jobTitle":"Nail Technician","id":22,"firstName":"Remi","lastName":"Holmes","hairColor":"Black","eyeColor":"Blue","age":42,"weight":61.2,"height":153,"sex":"M"},{"jobTitle":"Barber","id":23,"firstName":"Coleman","lastName":"Zimmerman","hairColor":"Brown","eyeColor":"Brown","age":59,"weight":74.6,"height":179,"sex":"M"},{"jobTitle":"Makeup Artist","id":24,"firstName":"Navya","lastName":"Anderson","hairColor":"Black","eyeColor":"Hazel","age":55,"weight":139.6,"height":152,"sex":"F"},{"jobTitle":"Office Manager","id":25,"firstName":"Lily","lastName":"Mendez","hairColor":"Black","eyeColor":"Green","age":57,"weight":105.2,"height":154,"sex":"F"},{"jobTitle":"Dietitian","id":26,"firstName":"Kareem","lastName":"Carrillo","hairColor":"Brown","eyeColor":"Brown","age":36,"weight":60.8,"height":177,"sex":"M"},{"jobTitle":"Tutor","id":27,"firstName":"Rishi","lastName":"Harris","hairColor":"Black","eyeColor":"Brown","age":43,"weight":67.2,"height":178,"sex":"M"},{"jobTitle":"Actuary","id":28,"firstName":"Elisha","lastName":"Patrick","hairColor":"Black","eyeColor":"Brown","age":38,"weight":83.6,"height":173,"sex":"M"},{"jobTitle":"Biological Engineer","id":29,"firstName":"Cristiano","lastName":"Robertson","hairColor":"Black","eyeColor":"Brown","age":47,"weight":80.2,"height":173,"sex":"M"},{"jobTitle":"Financial Services Representative","id":30,"firstName":"Lucien","lastName":"Robertson","hairColor":"Black","eyeColor":"Brown","age":44,"weight":76.8,"height":172,"sex":"M"},{"jobTitle":"Pilot","id":31,"firstName":"Dario","lastName":"Foley","hairColor":"Black","eyeColor":"Brown","age":30,"weight":121.2,"height":181,"sex":"M"},{"jobTitle":"Math Teacher","id":32,"firstName":"Kamari","lastName":"Edwards","hairColor":"Brown","eyeColor":"Brown","age":32,"weight":160.2,"height":174,"sex":"M"},{"jobTitle":"Front End Web Developer","id":33,"firstName":"Eimy","lastName":"Michael","hairColor":"Black","eyeColor":"Brown","age":41,"weight":143.8,"height":156,"sex":"F"},{"jobTitle":"Product Engineer","id":34,"firstName":"Jaelyn","lastName":"Olsen","hairColor":"Brown","eyeColor":"Brown","age":34,"weight":58.8,"height":152,"sex":"F"},{"jobTitle":"Retail Sales Associate","id":35,"firstName":"Angelo","lastName":"Olsen","hairColor":"Black","eyeColor":"Brown","age":31,"weight":146.4,"height":173,"sex":"M"},{"jobTitle":"Wedding Stylist","id":36,"firstName":"Caden","lastName":"Dudley","hairColor":"Black","eyeColor":"Brown","age":35,"weight":80.8,"height":172,"sex":"M"},{"jobTitle":"Floral Designer","id":37,"firstName":"Natalee","lastName":"Gay","hairColor":"Brown","eyeColor":"Brown","age":57,"weight":64.8,"height":167,"sex":"F"},{"jobTitle":"Nail Technician","id":38,"firstName":"Lux","lastName":"Reeves","hairColor":"Leverpostej","eyeColor":"Green","age":40,"weight":107.3,"height":169,"sex":"F"},{"jobTitle":"Graphic Designer","id":39,"firstName":"Ashlyn","lastName":"Reeves","hairColor":"Black","eyeColor":"Brown","age":50,"weight":84.8,"height":154,"sex":"F"},{"jobTitle":"Painter","id":40,"firstName":"Mikael","lastName":"Mejia","hairColor":"Black","eyeColor":"Blue","age":49,"weight":76.2,"height":168,"sex":"M"},{"jobTitle":"Housekeeper","id":41,"firstName":"Harlow","lastName":"Wang","hairColor":"Brown","eyeColor":"Brown","age":30,"weight":100.9,"height":177,"sex":"F"}]